benterfaces-0.1.1.dist-info/metadata.json
benterfaces-0.1.1.dist-info/DESCRIPTION.rst
benterfaces-0.1.1.dist-info/WHEEL
benterfaces-0.1.1.dist-info/METADATA
benterfaces-0.1.1.dist-info/top_level.txt
benterfaces-0.1.1.dist-info/RECORD
benterfaces/plugins.py
benterfaces/_test.py
benterfaces/decorators.py
benterfaces/__init__.py
