Metadata-Version: 2.0
Name: benterfaces
Version: 0.1.1
Summary: interface utilities
Home-page: https://github.com/bennr01/benterfaces/
Author: bennr01
Author-email: benjamin99.vogt@web.de
License: MIT
Keywords: interface interfaces utilities plugin plugins
Platform: UNKNOWN
Classifier: License :: OSI Approved :: MIT License
Classifier: Topic :: Utilities
Classifier: Topic :: Software Development :: Quality Assurance
Classifier: Topic :: Software Development :: Testing
Classifier: Programming Language :: Python
Classifier: Development Status :: 3 - Alpha
Classifier: Programming Language :: Python :: 2.6
Classifier: Programming Language :: Python :: 2.7
Classifier: Programming Language :: Python :: 3
Classifier: Programming Language :: Python :: 3.6
Classifier: Programming Language :: Python :: 3.7
Requires-Dist: zope.interface
